{
  "name": "Jeffrey Snover",
  "children": [
    {
      "name": "DJoin",
      "companyName": "Microsoft Corporation",
      "author": "Jeffrey Snover",
      "children": [
        {
          "name": "DomainJoinFile",
          "children": [
            {
              "name": "New-DomainJoinFile"
            }
          ]
        },
        {
          "name": "DomainUsingFile",
          "children": [
            {
              "name": "Join-DomainUsingFile"
            }
          ]
        }
      ]
    },
    {
      "name": "jpsgit",
      "companyName": "Unknown",
      "author": "Jeffrey Snover",
      "children": [
        {
          "name": "GitIssue",
          "children": [
            {
              "name": "Get-GitIssue"
            }
          ]
        },
        {
          "name": "ObjecttoClass",
          "children": [
            {
              "name": "Convert-ObjecttoClass"
            }
          ]
        }
      ]
    },
    {
      "name": "MetaProgramming",
      "companyName": "Microsoft",
      "author": "Jeffrey Snover",
      "children": [
        {
          "name": "ParameterAttribute",
          "children": [
            {
              "name": "New-ParameterAttribute"
            }
          ]
        },
        {
          "name": "ProxyCommand",
          "children": [
            {
              "name": "New-ProxyCommand"
            }
          ]
        }
      ]
    },
    {
      "name": "MSIgnite2016_PSV5Unplugged",
      "companyName": "Microsoft",
      "author": "Jeffrey Snover",
      "children": [
        {
          "name": "MSIgnite2016",
          "children": [
            {
              "name": "Show-MSIgnite2016"
            }
          ]
        }
      ]
    },
    {
      "name": "SpiceWorld2016_PowerShellUnplugged",
      "companyName": "Microsoft",
      "author": "Jeffrey Snover",
      "children": [
        {
          "name": "SpiceWorld2016",
          "children": [
            {
              "name": "Show-SpiceWorld2016"
            }
          ]
        }
      ]
    }
  ]
}
