{
  "name": "Collin Chaffin",
  "children": [
    {
      "name": "psFitb1t",
      "companyName": "Collin Chaffin",
      "author": "Collin Chaffin",
      "children": [
        {
          "name": "FitbitOAuthTokens",
          "children": [
            {
              "name": "Set-FitbitOAuthTokens"
            }
          ]
        },
        {
          "name": "HRdata",
          "children": [
            {
              "name": "Get-HRdata"
            }
          ]
        },
        {
          "name": "HRmonth",
          "children": [
            {
              "name": "Get-HRmonth"
            }
          ]
        }
      ]
    },
    {
      "name": "psWriteInformationColor",
      "companyName": "Collin Chaffin",
      "author": "Collin Chaffin",
      "children": [
        {
          "name": "InfoInColor",
          "children": [
            {
              "name": "Write-InfoInColor"
            }
          ]
        }
      ]
    }
  ]
}
