{
  "name": "Intility AS",
  "children": [
    {
      "name": "GlobalDashboardPS",
      "companyName": "Intility AS",
      "author": "Rudi Martinsen   Intility AS",
      "children": [
        {
          "name": "OVGDGroup",
          "children": [
            {
              "name": "New-OVGDGroup"
            },
            {
              "name": "Get-OVGDGroup"
            },
            {
              "name": "Remove-OVGDGroup"
            }
          ]
        },
        {
          "name": "OVGD",
          "children": [
            {
              "name": "Connect-OVGD"
            },
            {
              "name": "Disconnect-OVGD"
            }
          ]
        },
        {
          "name": "OVGDAppliance",
          "children": [
            {
              "name": "Get-OVGDAppliance"
            },
            {
              "name": "Add-OVGDAppliance"
            },
            {
              "name": "Set-OVGDAppliance"
            },
            {
              "name": "Remove-OVGDAppliance"
            }
          ]
        },
        {
          "name": "OVGDCertificate",
          "children": [
            {
              "name": "Get-OVGDCertificate"
            }
          ]
        },
        {
          "name": "OVGDConvergedSystem",
          "children": [
            {
              "name": "Get-OVGDConvergedSystem"
            }
          ]
        },
        {
          "name": "OVGDEnclosure",
          "children": [
            {
              "name": "Get-OVGDEnclosure"
            }
          ]
        },
        {
          "name": "OVGDGroupMember",
          "children": [
            {
              "name": "Get-OVGDGroupMember"
            }
          ]
        },
        {
          "name": "OVGDServerHardware",
          "children": [
            {
              "name": "Get-OVGDServerHardware"
            }
          ]
        },
        {
          "name": "OVGDServerProfile",
          "children": [
            {
              "name": "Get-OVGDServerProfile"
            }
          ]
        },
        {
          "name": "OVGDServerProfileTemplate",
          "children": [
            {
              "name": "Get-OVGDServerProfileTemplate"
            }
          ]
        },
        {
          "name": "OVGDStorageSystem",
          "children": [
            {
              "name": "Get-OVGDStorageSystem"
            }
          ]
        },
        {
          "name": "OVGDSessionKey",
          "children": [
            {
              "name": "New-OVGDSessionKey"
            },
            {
              "name": "Remove-OVGDSessionKey"
            }
          ]
        },
        {
          "name": "OVGDResourceAlert",
          "children": [
            {
              "name": "Get-OVGDResourceAlert"
            }
          ]
        },
        {
          "name": "OVGDTask",
          "children": [
            {
              "name": "Get-OVGDTask"
            }
          ]
        },
        {
          "name": "OVGDStorageVolume",
          "children": [
            {
              "name": "Get-OVGDStorageVolume"
            }
          ]
        },
        {
          "name": "OVGDStoragePool",
          "children": [
            {
              "name": "Get-OVGDStoragePool"
            }
          ]
        },
        {
          "name": "OVGDSANManager",
          "children": [
            {
              "name": "Get-OVGDSANManager"
            }
          ]
        },
        {
          "name": "OVGDManagedSAN",
          "children": [
            {
              "name": "Get-OVGDManagedSAN"
            }
          ]
        }
      ]
    },
    {
      "name": "PSAuthClient",
      "companyName": "Intility AS",
      "author": "Alf L kken",
      "children": [
        {
          "name": "WebView2Cache",
          "children": [
            {
              "name": "Clear-WebView2Cache"
            }
          ]
        },
        {
          "name": "JsonWebToken",
          "children": [
            {
              "name": "ConvertFrom-JsonWebToken"
            }
          ]
        },
        {
          "name": "OidcDiscoveryMetadata",
          "children": [
            {
              "name": "Get-OidcDiscoveryMetadata"
            }
          ]
        },
        {
          "name": "OAuth2AuthorizationEndpoint",
          "children": [
            {
              "name": "Invoke-OAuth2AuthorizationEndpoint"
            }
          ]
        },
        {
          "name": "OAuth2DeviceAuthorizationEndpoint",
          "children": [
            {
              "name": "Invoke-OAuth2DeviceAuthorizationEndpoint"
            }
          ]
        },
        {
          "name": "OAuth2TokenEndpoint",
          "children": [
            {
              "name": "Invoke-OAuth2TokenEndpoint"
            }
          ]
        },
        {
          "name": "Oauth2JwtAssertion",
          "children": [
            {
              "name": "New-Oauth2JwtAssertion"
            }
          ]
        },
        {
          "name": "PkceChallenge",
          "children": [
            {
              "name": "New-PkceChallenge"
            }
          ]
        },
        {
          "name": "JsonWebTokenSignature",
          "children": [
            {
              "name": "Test-JsonWebTokenSignature"
            }
          ]
        }
      ]
    }
  ]
}
