{
  "name": "Glenn Sarti",
  "children": [
    {
      "name": "JiraHelper",
      "companyName": "Glenn Sarti",
      "author": "Glenn Sarti",
      "children": [
        {
          "name": "Jira",
          "children": [
            {
              "name": "Invoke-Jira"
            }
          ]
        }
      ]
    },
    {
      "name": "RubyInstaller",
      "companyName": "Community",
      "author": "Glenn Sarti",
      "children": [
        {
          "name": "Ruby",
          "children": [
            {
              "name": "Get-Ruby"
            },
            {
              "name": "Install-Ruby"
            },
            {
              "name": "Select-Ruby"
            }
          ]
        }
      ]
    }
  ]
}
