{
  "name": "John Kerski",
  "children": [
    {
      "name": "Invoke-DQVTesting",
      "companyName": "kerski.tech",
      "author": "John Kerski",
      "children": [
        {
          "name": "DQVTesting",
          "children": [
            {
              "name": "Invoke-DQVTesting"
            }
          ]
        }
      ]
    },
    {
      "name": "Invoke-SemanticModelRefresh",
      "companyName": "kerski.tech",
      "author": "John Kerski",
      "children": [
        {
          "name": "SemanticModelRefresh",
          "children": [
            {
              "name": "Invoke-SemanticModelRefresh"
            }
          ]
        }
      ]
    }
  ]
}
