{
  "name": "psdevuk wsl2001",
  "children": [
    {
      "name": "UniversalDashboard.UDButtonLoader",
      "companyName": "Ironman Software, LLC",
      "author": "psdevuk wsl2001",
      "children": [
        {
          "name": "UDButtonLoader",
          "children": [
            {
              "name": "New-UDButtonLoader"
            }
          ]
        }
      ]
    },
    {
      "name": "UniversalDashboard.UDButtonParticle",
      "companyName": "Ironman Software, LLC",
      "author": "psdevuk wsl2001",
      "children": [
        {
          "name": "UDButtonParticle",
          "children": [
            {
              "name": "New-UDButtonParticle"
            }
          ]
        }
      ]
    }
  ]
}
