{
  "name": "Dawan",
  "children": [
    {
      "name": "ICMP",
      "companyName": "Dawan",
      "author": "David CLEMENT",
      "children": [
        {
          "name": "ICMP",
          "children": [
            {
              "name": "Test-ICMP"
            }
          ]
        }
      ]
    },
    {
      "name": "IPv4Range",
      "companyName": "Dawan",
      "author": "David CLEMENT",
      "children": [
        {
          "name": "IPv4Range",
          "children": [
            {
              "name": "Get-IPv4Range"
            }
          ]
        },
        {
          "name": "IPv4Info",
          "children": [
            {
              "name": "Get-IPv4Info"
            }
          ]
        }
      ]
    },
    {
      "name": "routines",
      "companyName": "Dawan",
      "author": "DClementDawan",
      "children": [
        {
          "name": "AdminPrivilege",
          "children": [
            {
              "name": "Test-AdminPrivilege"
            }
          ]
        },
        {
          "name": "Password",
          "children": [
            {
              "name": "Get-Password"
            }
          ]
        },
        {
          "name": "String",
          "children": [
            {
              "name": "Clear-String"
            }
          ]
        },
        {
          "name": "Diacritics",
          "children": [
            {
              "name": "Remove-Diacritics"
            }
          ]
        },
        {
          "name": "PopUp",
          "children": [
            {
              "name": "Read-PopUp"
            }
          ]
        },
        {
          "name": "Choice",
          "children": [
            {
              "name": "Read-Choice"
            }
          ]
        },
        {
          "name": "IPv4Range",
          "children": [
            {
              "name": "Get-IPv4Range"
            }
          ]
        },
        {
          "name": "IPv4Info",
          "children": [
            {
              "name": "Get-IPv4Info"
            }
          ]
        },
        {
          "name": "ICMP",
          "children": [
            {
              "name": "Test-ICMP"
            }
          ]
        },
        {
          "name": "HVClone",
          "children": [
            {
              "name": "New-HVClone"
            }
          ]
        }
      ]
    }
  ]
}
