{
  "name": "openapitools.org",
  "children": [
    {
      "name": "PSOpenAPITools",
      "companyName": "openapitools.org",
      "author": "OpenAPI Generator Team",
      "children": [
        {
          "name": "Pet",
          "children": [
            {
              "name": "Add-Pet"
            },
            {
              "name": "Update-Pet"
            },
            {
              "name": "Initialize-Pet"
            }
          ]
        },
        {
          "name": "DeletePet",
          "children": [
            {
              "name": "Invoke-DeletePet"
            }
          ]
        },
        {
          "name": "PetsByStatus",
          "children": [
            {
              "name": "Find-PetsByStatus"
            }
          ]
        },
        {
          "name": "PetsByTags",
          "children": [
            {
              "name": "Find-PetsByTags"
            }
          ]
        },
        {
          "name": "PetById",
          "children": [
            {
              "name": "Get-PetById"
            }
          ]
        },
        {
          "name": "PetWithForm",
          "children": [
            {
              "name": "Update-PetWithForm"
            }
          ]
        },
        {
          "name": "UploadFile",
          "children": [
            {
              "name": "Invoke-UploadFile"
            }
          ]
        },
        {
          "name": "DeleteOrder",
          "children": [
            {
              "name": "Invoke-DeleteOrder"
            }
          ]
        },
        {
          "name": "Inventory",
          "children": [
            {
              "name": "Get-Inventory"
            }
          ]
        },
        {
          "name": "OrderById",
          "children": [
            {
              "name": "Get-OrderById"
            }
          ]
        },
        {
          "name": "PlaceOrder",
          "children": [
            {
              "name": "Invoke-PlaceOrder"
            }
          ]
        },
        {
          "name": "User",
          "children": [
            {
              "name": "New-User"
            },
            {
              "name": "Update-User"
            },
            {
              "name": "Initialize-User"
            }
          ]
        },
        {
          "name": "UsersWithArrayInput",
          "children": [
            {
              "name": "New-UsersWithArrayInput"
            }
          ]
        },
        {
          "name": "UsersWithListInput",
          "children": [
            {
              "name": "New-UsersWithListInput"
            }
          ]
        },
        {
          "name": "DeleteUser",
          "children": [
            {
              "name": "Invoke-DeleteUser"
            }
          ]
        },
        {
          "name": "UserByName",
          "children": [
            {
              "name": "Get-UserByName"
            }
          ]
        },
        {
          "name": "LoginUser",
          "children": [
            {
              "name": "Invoke-LoginUser"
            }
          ]
        },
        {
          "name": "LogoutUser",
          "children": [
            {
              "name": "Invoke-LogoutUser"
            }
          ]
        },
        {
          "name": "ApiResponse",
          "children": [
            {
              "name": "Initialize-ApiResponse"
            }
          ]
        },
        {
          "name": "JsonToApiResponse",
          "children": [
            {
              "name": "ConvertFrom-JsonToApiResponse"
            }
          ]
        },
        {
          "name": "Category",
          "children": [
            {
              "name": "Initialize-Category"
            }
          ]
        },
        {
          "name": "JsonToCategory",
          "children": [
            {
              "name": "ConvertFrom-JsonToCategory"
            }
          ]
        },
        {
          "name": "InlineObject",
          "children": [
            {
              "name": "Initialize-InlineObject"
            }
          ]
        },
        {
          "name": "JsonToInlineObject",
          "children": [
            {
              "name": "ConvertFrom-JsonToInlineObject"
            }
          ]
        },
        {
          "name": "InlineObject1",
          "children": [
            {
              "name": "Initialize-InlineObject1"
            }
          ]
        },
        {
          "name": "JsonToInlineObject1",
          "children": [
            {
              "name": "ConvertFrom-JsonToInlineObject1"
            }
          ]
        },
        {
          "name": "Order",
          "children": [
            {
              "name": "Initialize-Order"
            }
          ]
        },
        {
          "name": "JsonToOrder",
          "children": [
            {
              "name": "ConvertFrom-JsonToOrder"
            }
          ]
        },
        {
          "name": "JsonToPet",
          "children": [
            {
              "name": "ConvertFrom-JsonToPet"
            }
          ]
        },
        {
          "name": "Tag",
          "children": [
            {
              "name": "Initialize-Tag"
            }
          ]
        },
        {
          "name": "JsonToTag",
          "children": [
            {
              "name": "ConvertFrom-JsonToTag"
            }
          ]
        },
        {
          "name": "JsonToUser",
          "children": [
            {
              "name": "ConvertFrom-JsonToUser"
            }
          ]
        },
        {
          "name": "Configuration",
          "children": [
            {
              "name": "Get-Configuration"
            },
            {
              "name": "Set-Configuration"
            }
          ]
        },
        {
          "name": "ConfigurationApiKey",
          "children": [
            {
              "name": "Set-ConfigurationApiKey"
            }
          ]
        },
        {
          "name": "ConfigurationApiKeyPrefix",
          "children": [
            {
              "name": "Set-ConfigurationApiKeyPrefix"
            }
          ]
        },
        {
          "name": "ConfigurationDefaultHeader",
          "children": [
            {
              "name": "Set-ConfigurationDefaultHeader"
            }
          ]
        },
        {
          "name": "HostSetting",
          "children": [
            {
              "name": "Get-HostSetting"
            }
          ]
        },
        {
          "name": "UrlFromHostSetting",
          "children": [
            {
              "name": "Get-UrlFromHostSetting"
            }
          ]
        },
        {
          "name": "ConfigurationHttpSigning",
          "children": [
            {
              "name": "Set-ConfigurationHttpSigning"
            },
            {
              "name": "Get-ConfigurationHttpSigning"
            }
          ]
        }
      ]
    },
    {
      "name": "PSPetstoreDemo",
      "companyName": "openapitools.org",
      "author": "OpenAPI Generator Team",
      "children": [
        {
          "name": "Pet",
          "children": [
            {
              "name": "Add-Pet"
            },
            {
              "name": "Update-Pet"
            },
            {
              "name": "Initialize-Pet"
            }
          ]
        },
        {
          "name": "DeletePet",
          "children": [
            {
              "name": "Invoke-DeletePet"
            }
          ]
        },
        {
          "name": "PetsByStatus",
          "children": [
            {
              "name": "Find-PetsByStatus"
            }
          ]
        },
        {
          "name": "PetsByTags",
          "children": [
            {
              "name": "Find-PetsByTags"
            }
          ]
        },
        {
          "name": "PetById",
          "children": [
            {
              "name": "Get-PetById"
            }
          ]
        },
        {
          "name": "PetWithForm",
          "children": [
            {
              "name": "Update-PetWithForm"
            }
          ]
        },
        {
          "name": "UploadFile",
          "children": [
            {
              "name": "Invoke-UploadFile"
            }
          ]
        },
        {
          "name": "DeleteOrder",
          "children": [
            {
              "name": "Invoke-DeleteOrder"
            }
          ]
        },
        {
          "name": "Inventory",
          "children": [
            {
              "name": "Get-Inventory"
            }
          ]
        },
        {
          "name": "OrderById",
          "children": [
            {
              "name": "Get-OrderById"
            }
          ]
        },
        {
          "name": "PlaceOrder",
          "children": [
            {
              "name": "Invoke-PlaceOrder"
            }
          ]
        },
        {
          "name": "User",
          "children": [
            {
              "name": "New-User"
            },
            {
              "name": "Update-User"
            },
            {
              "name": "Initialize-User"
            }
          ]
        },
        {
          "name": "UsersWithArrayInput",
          "children": [
            {
              "name": "New-UsersWithArrayInput"
            }
          ]
        },
        {
          "name": "UsersWithListInput",
          "children": [
            {
              "name": "New-UsersWithListInput"
            }
          ]
        },
        {
          "name": "DeleteUser",
          "children": [
            {
              "name": "Invoke-DeleteUser"
            }
          ]
        },
        {
          "name": "UserByName",
          "children": [
            {
              "name": "Get-UserByName"
            }
          ]
        },
        {
          "name": "LoginUser",
          "children": [
            {
              "name": "Invoke-LoginUser"
            }
          ]
        },
        {
          "name": "LogoutUser",
          "children": [
            {
              "name": "Invoke-LogoutUser"
            }
          ]
        },
        {
          "name": "ApiResponse",
          "children": [
            {
              "name": "Initialize-ApiResponse"
            }
          ]
        },
        {
          "name": "JsonToApiResponse",
          "children": [
            {
              "name": "ConvertFrom-JsonToApiResponse"
            }
          ]
        },
        {
          "name": "Category",
          "children": [
            {
              "name": "Initialize-Category"
            }
          ]
        },
        {
          "name": "JsonToCategory",
          "children": [
            {
              "name": "ConvertFrom-JsonToCategory"
            }
          ]
        },
        {
          "name": "Order",
          "children": [
            {
              "name": "Initialize-Order"
            }
          ]
        },
        {
          "name": "JsonToOrder",
          "children": [
            {
              "name": "ConvertFrom-JsonToOrder"
            }
          ]
        },
        {
          "name": "JsonToPet",
          "children": [
            {
              "name": "ConvertFrom-JsonToPet"
            }
          ]
        },
        {
          "name": "Tag",
          "children": [
            {
              "name": "Initialize-Tag"
            }
          ]
        },
        {
          "name": "JsonToTag",
          "children": [
            {
              "name": "ConvertFrom-JsonToTag"
            }
          ]
        },
        {
          "name": "JsonToUser",
          "children": [
            {
              "name": "ConvertFrom-JsonToUser"
            }
          ]
        },
        {
          "name": "Configuration",
          "children": [
            {
              "name": "Get-Configuration"
            },
            {
              "name": "Set-Configuration"
            }
          ]
        },
        {
          "name": "ConfigurationApiKey",
          "children": [
            {
              "name": "Set-ConfigurationApiKey"
            }
          ]
        },
        {
          "name": "ConfigurationApiKeyPrefix",
          "children": [
            {
              "name": "Set-ConfigurationApiKeyPrefix"
            }
          ]
        },
        {
          "name": "ConfigurationDefaultHeader",
          "children": [
            {
              "name": "Set-ConfigurationDefaultHeader"
            }
          ]
        },
        {
          "name": "HostSetting",
          "children": [
            {
              "name": "Get-HostSetting"
            }
          ]
        },
        {
          "name": "UrlFromHostSetting",
          "children": [
            {
              "name": "Get-UrlFromHostSetting"
            }
          ]
        },
        {
          "name": "ConfigurationHttpSigning",
          "children": [
            {
              "name": "Set-ConfigurationHttpSigning"
            },
            {
              "name": "Get-ConfigurationHttpSigning"
            }
          ]
        }
      ]
    },
    {
      "name": "TorizonPlatformAPI",
      "companyName": "openapitools.org",
      "author": "OpenAPI Generator Team",
      "children": [
        {
          "name": "TorizonPlatformAPIDeviceDataDevicesDeviceuuidMetrics",
          "children": [
            {
              "name": "Get-TorizonPlatformAPIDeviceDataDevicesDeviceuuidMetrics"
            }
          ]
        },
        {
          "name": "TorizonPlatformAPIDeviceDataFleetsFleetidMetrics",
          "children": [
            {
              "name": "Get-TorizonPlatformAPIDeviceDataFleetsFleetidMetrics"
            }
          ]
        },
        {
          "name": "TorizonPlatformAPIDeviceDataMetricNames",
          "children": [
            {
              "name": "Get-TorizonPlatformAPIDeviceDataMetricNames"
            }
          ]
        },
        {
          "name": "TorizonPlatformAPIDeleteDevicesDeviceuuid",
          "children": [
            {
              "name": "Invoke-TorizonPlatformAPIDeleteDevicesDeviceuuid"
            }
          ]
        },
        {
          "name": "TorizonPlatformAPIDevices",
          "children": [
            {
              "name": "Get-TorizonPlatformAPIDevices"
            },
            {
              "name": "Submit-TorizonPlatformAPIDevices"
            }
          ]
        },
        {
          "name": "TorizonPlatformAPIDevicesDeviceuuid",
          "children": [
            {
              "name": "Get-TorizonPlatformAPIDevicesDeviceuuid"
            }
          ]
        },
        {
          "name": "TorizonPlatformAPIDevicesNameDeviceuuid",
          "children": [
            {
              "name": "Get-TorizonPlatformAPIDevicesNameDeviceuuid"
            },
            {
              "name": "Send-TorizonPlatformAPIDevicesNameDeviceuuid"
            }
          ]
        },
        {
          "name": "TorizonPlatformAPIDevicesNetwork",
          "children": [
            {
              "name": "Get-TorizonPlatformAPIDevicesNetwork"
            }
          ]
        },
        {
          "name": "TorizonPlatformAPIDevicesNetworkDeviceuuid",
          "children": [
            {
              "name": "Get-TorizonPlatformAPIDevicesNetworkDeviceuuid"
            }
          ]
        },
        {
          "name": "TorizonPlatformAPIDevicesNotesDeviceuuid",
          "children": [
            {
              "name": "Get-TorizonPlatformAPIDevicesNotesDeviceuuid"
            },
            {
              "name": "Send-TorizonPlatformAPIDevicesNotesDeviceuuid"
            }
          ]
        },
        {
          "name": "TorizonPlatformAPIDevicesPackages",
          "children": [
            {
              "name": "Get-TorizonPlatformAPIDevicesPackages"
            }
          ]
        },
        {
          "name": "TorizonPlatformAPIDevicesPackagesDeviceuuid",
          "children": [
            {
              "name": "Get-TorizonPlatformAPIDevicesPackagesDeviceuuid"
            }
          ]
        },
        {
          "name": "TorizonPlatformAPIDevicesToken",
          "children": [
            {
              "name": "Get-TorizonPlatformAPIDevicesToken"
            }
          ]
        },
        {
          "name": "TorizonPlatformAPIDevicesUptaneDeviceuuidAssignment",
          "children": [
            {
              "name": "Get-TorizonPlatformAPIDevicesUptaneDeviceuuidAssignment"
            }
          ]
        },
        {
          "name": "TorizonPlatformAPIDevicesUptaneDeviceuuidComponents",
          "children": [
            {
              "name": "Get-TorizonPlatformAPIDevicesUptaneDeviceuuidComponents"
            }
          ]
        },
        {
          "name": "TorizonPlatformAPIDeleteFleetsFleetid",
          "children": [
            {
              "name": "Invoke-TorizonPlatformAPIDeleteFleetsFleetid"
            }
          ]
        },
        {
          "name": "TorizonPlatformAPIDeleteFleetsFleetidDevices",
          "children": [
            {
              "name": "Invoke-TorizonPlatformAPIDeleteFleetsFleetidDevices"
            }
          ]
        },
        {
          "name": "TorizonPlatformAPIFleets",
          "children": [
            {
              "name": "Get-TorizonPlatformAPIFleets"
            },
            {
              "name": "Submit-TorizonPlatformAPIFleets"
            }
          ]
        },
        {
          "name": "TorizonPlatformAPIFleetsFleetidDevices",
          "children": [
            {
              "name": "Get-TorizonPlatformAPIFleetsFleetidDevices"
            },
            {
              "name": "Submit-TorizonPlatformAPIFleetsFleetidDevices"
            }
          ]
        },
        {
          "name": "TorizonPlatformAPIDeletePackagesPackageid",
          "children": [
            {
              "name": "Invoke-TorizonPlatformAPIDeletePackagesPackageid"
            }
          ]
        },
        {
          "name": "TorizonPlatformAPIPackages",
          "children": [
            {
              "name": "Get-TorizonPlatformAPIPackages"
            },
            {
              "name": "Submit-TorizonPlatformAPIPackages"
            }
          ]
        },
        {
          "name": "TorizonPlatformAPIPackagesExternal",
          "children": [
            {
              "name": "Get-TorizonPlatformAPIPackagesExternal"
            }
          ]
        },
        {
          "name": "TorizonPlatformAPIPackagesExternalInfo",
          "children": [
            {
              "name": "Get-TorizonPlatformAPIPackagesExternalInfo"
            }
          ]
        },
        {
          "name": "TorizonPlatformAPIPackagesExternalRefreshSourceFileName",
          "children": [
            {
              "name": "Get-TorizonPlatformAPIPackagesExternalRefreshSourceFileName"
            }
          ]
        },
        {
          "name": "TorizonPlatformAPIPatchPackagesPackageid",
          "children": [
            {
              "name": "Invoke-TorizonPlatformAPIPatchPackagesPackageid"
            }
          ]
        },
        {
          "name": "TorizonPlatformAPILockboxDetails",
          "children": [
            {
              "name": "Get-TorizonPlatformAPILockboxDetails"
            }
          ]
        },
        {
          "name": "TorizonPlatformAPILockboxes",
          "children": [
            {
              "name": "Get-TorizonPlatformAPILockboxes"
            }
          ]
        },
        {
          "name": "TorizonPlatformAPILockboxesLockboxName",
          "children": [
            {
              "name": "Get-TorizonPlatformAPILockboxesLockboxName"
            },
            {
              "name": "Submit-TorizonPlatformAPILockboxesLockboxName"
            }
          ]
        },
        {
          "name": "TorizonPlatformAPIPatchUpdates",
          "children": [
            {
              "name": "Invoke-TorizonPlatformAPIPatchUpdates"
            }
          ]
        },
        {
          "name": "TorizonPlatformAPIUpdates",
          "children": [
            {
              "name": "Submit-TorizonPlatformAPIUpdates"
            }
          ]
        },
        {
          "name": "TorizonPlatformAPIBadRequestRepr",
          "children": [
            {
              "name": "Initialize-TorizonPlatformAPIBadRequestRepr"
            }
          ]
        },
        {
          "name": "TorizonPlatformAPIJsonToBadRequestRepr",
          "children": [
            {
              "name": "ConvertFrom-TorizonPlatformAPIJsonToBadRequestRepr"
            }
          ]
        },
        {
          "name": "TorizonPlatformAPIClientSignature",
          "children": [
            {
              "name": "Initialize-TorizonPlatformAPIClientSignature"
            }
          ]
        },
        {
          "name": "TorizonPlatformAPIJsonToClientSignature",
          "children": [
            {
              "name": "ConvertFrom-TorizonPlatformAPIJsonToClientSignature"
            }
          ]
        },
        {
          "name": "TorizonPlatformAPIConflictRepr",
          "children": [
            {
              "name": "Initialize-TorizonPlatformAPIConflictRepr"
            }
          ]
        },
        {
          "name": "TorizonPlatformAPIJsonToConflictRepr",
          "children": [
            {
              "name": "ConvertFrom-TorizonPlatformAPIJsonToConflictRepr"
            }
          ]
        },
        {
          "name": "TorizonPlatformAPICreateFleet",
          "children": [
            {
              "name": "Initialize-TorizonPlatformAPICreateFleet"
            }
          ]
        },
        {
          "name": "TorizonPlatformAPIJsonToCreateFleet",
          "children": [
            {
              "name": "ConvertFrom-TorizonPlatformAPIJsonToCreateFleet"
            }
          ]
        },
        {
          "name": "TorizonPlatformAPICreateLockboxRequest",
          "children": [
            {
              "name": "Initialize-TorizonPlatformAPICreateLockboxRequest"
            }
          ]
        },
        {
          "name": "TorizonPlatformAPIJsonToCreateLockboxRequest",
          "children": [
            {
              "name": "ConvertFrom-TorizonPlatformAPIJsonToCreateLockboxRequest"
            }
          ]
        },
        {
          "name": "TorizonPlatformAPICustomUpdateData",
          "children": [
            {
              "name": "Initialize-TorizonPlatformAPICustomUpdateData"
            }
          ]
        },
        {
          "name": "TorizonPlatformAPIJsonToCustomUpdateData",
          "children": [
            {
              "name": "ConvertFrom-TorizonPlatformAPIJsonToCustomUpdateData"
            }
          ]
        },
        {
          "name": "TorizonPlatformAPIDelegationInfo",
          "children": [
            {
              "name": "Initialize-TorizonPlatformAPIDelegationInfo"
            }
          ]
        },
        {
          "name": "TorizonPlatformAPIJsonToDelegationInfo",
          "children": [
            {
              "name": "ConvertFrom-TorizonPlatformAPIJsonToDelegationInfo"
            }
          ]
        },
        {
          "name": "TorizonPlatformAPIDeviceCreateReq",
          "children": [
            {
              "name": "Initialize-TorizonPlatformAPIDeviceCreateReq"
            }
          ]
        },
        {
          "name": "TorizonPlatformAPIJsonToDeviceCreateReq",
          "children": [
            {
              "name": "ConvertFrom-TorizonPlatformAPIJsonToDeviceCreateReq"
            }
          ]
        },
        {
          "name": "TorizonPlatformAPIDeviceInfoBasic",
          "children": [
            {
              "name": "Initialize-TorizonPlatformAPIDeviceInfoBasic"
            }
          ]
        },
        {
          "name": "TorizonPlatformAPIJsonToDeviceInfoBasic",
          "children": [
            {
              "name": "ConvertFrom-TorizonPlatformAPIJsonToDeviceInfoBasic"
            }
          ]
        },
        {
          "name": "TorizonPlatformAPIDeviceInfoExtended",
          "children": [
            {
              "name": "Initialize-TorizonPlatformAPIDeviceInfoExtended"
            }
          ]
        },
        {
          "name": "TorizonPlatformAPIJsonToDeviceInfoExtended",
          "children": [
            {
              "name": "ConvertFrom-TorizonPlatformAPIJsonToDeviceInfoExtended"
            }
          ]
        },
        {
          "name": "TorizonPlatformAPIDevicePackage",
          "children": [
            {
              "name": "Initialize-TorizonPlatformAPIDevicePackage"
            }
          ]
        },
        {
          "name": "TorizonPlatformAPIJsonToDevicePackage",
          "children": [
            {
              "name": "ConvertFrom-TorizonPlatformAPIJsonToDevicePackage"
            }
          ]
        },
        {
          "name": "TorizonPlatformAPIDevicePackages",
          "children": [
            {
              "name": "Initialize-TorizonPlatformAPIDevicePackages"
            }
          ]
        },
        {
          "name": "TorizonPlatformAPIJsonToDevicePackages",
          "children": [
            {
              "name": "ConvertFrom-TorizonPlatformAPIJsonToDevicePackages"
            }
          ]
        },
        {
          "name": "TorizonPlatformAPIEcuInfoImage",
          "children": [
            {
              "name": "Initialize-TorizonPlatformAPIEcuInfoImage"
            }
          ]
        },
        {
          "name": "TorizonPlatformAPIJsonToEcuInfoImage",
          "children": [
            {
              "name": "ConvertFrom-TorizonPlatformAPIJsonToEcuInfoImage"
            }
          ]
        },
        {
          "name": "TorizonPlatformAPIEcuInfoResponse",
          "children": [
            {
              "name": "Initialize-TorizonPlatformAPIEcuInfoResponse"
            }
          ]
        },
        {
          "name": "TorizonPlatformAPIJsonToEcuInfoResponse",
          "children": [
            {
              "name": "ConvertFrom-TorizonPlatformAPIJsonToEcuInfoResponse"
            }
          ]
        },
        {
          "name": "TorizonPlatformAPIEditPackage",
          "children": [
            {
              "name": "Initialize-TorizonPlatformAPIEditPackage"
            }
          ]
        },
        {
          "name": "TorizonPlatformAPIJsonToEditPackage",
          "children": [
            {
              "name": "ConvertFrom-TorizonPlatformAPIJsonToEditPackage"
            }
          ]
        },
        {
          "name": "TorizonPlatformAPIErrorRepresentation",
          "children": [
            {
              "name": "Initialize-TorizonPlatformAPIErrorRepresentation"
            }
          ]
        },
        {
          "name": "TorizonPlatformAPIJsonToErrorRepresentation",
          "children": [
            {
              "name": "ConvertFrom-TorizonPlatformAPIJsonToErrorRepresentation"
            }
          ]
        },
        {
          "name": "TorizonPlatformAPIExternalPackage",
          "children": [
            {
              "name": "Initialize-TorizonPlatformAPIExternalPackage"
            }
          ]
        },
        {
          "name": "TorizonPlatformAPIJsonToExternalPackage",
          "children": [
            {
              "name": "ConvertFrom-TorizonPlatformAPIJsonToExternalPackage"
            }
          ]
        },
        {
          "name": "TorizonPlatformAPIFileInfo",
          "children": [
            {
              "name": "Initialize-TorizonPlatformAPIFileInfo"
            }
          ]
        },
        {
          "name": "TorizonPlatformAPIJsonToFileInfo",
          "children": [
            {
              "name": "ConvertFrom-TorizonPlatformAPIJsonToFileInfo"
            }
          ]
        },
        {
          "name": "TorizonPlatformAPIFleet",
          "children": [
            {
              "name": "Initialize-TorizonPlatformAPIFleet"
            }
          ]
        },
        {
          "name": "TorizonPlatformAPIJsonToFleet",
          "children": [
            {
              "name": "ConvertFrom-TorizonPlatformAPIJsonToFleet"
            }
          ]
        },
        {
          "name": "TorizonPlatformAPIImage",
          "children": [
            {
              "name": "Initialize-TorizonPlatformAPIImage"
            }
          ]
        },
        {
          "name": "TorizonPlatformAPIJsonToImage",
          "children": [
            {
              "name": "ConvertFrom-TorizonPlatformAPIJsonToImage"
            }
          ]
        },
        {
          "name": "TorizonPlatformAPIInstalledPackage",
          "children": [
            {
              "name": "Initialize-TorizonPlatformAPIInstalledPackage"
            }
          ]
        },
        {
          "name": "TorizonPlatformAPIJsonToInstalledPackage",
          "children": [
            {
              "name": "ConvertFrom-TorizonPlatformAPIJsonToInstalledPackage"
            }
          ]
        },
        {
          "name": "TorizonPlatformAPIJsonSignedPayload",
          "children": [
            {
              "name": "Initialize-TorizonPlatformAPIJsonSignedPayload"
            }
          ]
        },
        {
          "name": "TorizonPlatformAPIJsonToJsonSignedPayload",
          "children": [
            {
              "name": "ConvertFrom-TorizonPlatformAPIJsonToJsonSignedPayload"
            }
          ]
        },
        {
          "name": "TorizonPlatformAPIMetricsResponse",
          "children": [
            {
              "name": "Initialize-TorizonPlatformAPIMetricsResponse"
            }
          ]
        },
        {
          "name": "TorizonPlatformAPIJsonToMetricsResponse",
          "children": [
            {
              "name": "ConvertFrom-TorizonPlatformAPIJsonToMetricsResponse"
            }
          ]
        },
        {
          "name": "TorizonPlatformAPINetworkInfo",
          "children": [
            {
              "name": "Initialize-TorizonPlatformAPINetworkInfo"
            }
          ]
        },
        {
          "name": "TorizonPlatformAPIJsonToNetworkInfo",
          "children": [
            {
              "name": "ConvertFrom-TorizonPlatformAPIJsonToNetworkInfo"
            }
          ]
        },
        {
          "name": "TorizonPlatformAPINotFoundRepr",
          "children": [
            {
              "name": "Initialize-TorizonPlatformAPINotFoundRepr"
            }
          ]
        },
        {
          "name": "TorizonPlatformAPIJsonToNotFoundRepr",
          "children": [
            {
              "name": "ConvertFrom-TorizonPlatformAPIJsonToNotFoundRepr"
            }
          ]
        },
        {
          "name": "TorizonPlatformAPIPackage",
          "children": [
            {
              "name": "Initialize-TorizonPlatformAPIPackage"
            }
          ]
        },
        {
          "name": "TorizonPlatformAPIJsonToPackage",
          "children": [
            {
              "name": "ConvertFrom-TorizonPlatformAPIJsonToPackage"
            }
          ]
        },
        {
          "name": "TorizonPlatformAPIPackageInfo",
          "children": [
            {
              "name": "Initialize-TorizonPlatformAPIPackageInfo"
            }
          ]
        },
        {
          "name": "TorizonPlatformAPIJsonToPackageInfo",
          "children": [
            {
              "name": "ConvertFrom-TorizonPlatformAPIJsonToPackageInfo"
            }
          ]
        },
        {
          "name": "TorizonPlatformAPIPaginationResultDeviceInfoBasic",
          "children": [
            {
              "name": "Initialize-TorizonPlatformAPIPaginationResultDeviceInfoBasic"
            }
          ]
        },
        {
          "name": "TorizonPlatformAPIJsonToPaginationResultDeviceInfoBasic",
          "children": [
            {
              "name": "ConvertFrom-TorizonPlatformAPIJsonToPaginationResultDeviceInfoBasic"
            }
          ]
        },
        {
          "name": "TorizonPlatformAPIPaginationResultDevicePackages",
          "children": [
            {
              "name": "Initialize-TorizonPlatformAPIPaginationResultDevicePackages"
            }
          ]
        },
        {
          "name": "TorizonPlatformAPIJsonToPaginationResultDevicePackages",
          "children": [
            {
              "name": "ConvertFrom-TorizonPlatformAPIJsonToPaginationResultDevicePackages"
            }
          ]
        },
        {
          "name": "TorizonPlatformAPIPaginationResultExternalPackage",
          "children": [
            {
              "name": "Initialize-TorizonPlatformAPIPaginationResultExternalPackage"
            }
          ]
        },
        {
          "name": "TorizonPlatformAPIJsonToPaginationResultExternalPackage",
          "children": [
            {
              "name": "ConvertFrom-TorizonPlatformAPIJsonToPaginationResultExternalPackage"
            }
          ]
        },
        {
          "name": "TorizonPlatformAPIPaginationResultFleet",
          "children": [
            {
              "name": "Initialize-TorizonPlatformAPIPaginationResultFleet"
            }
          ]
        },
        {
          "name": "TorizonPlatformAPIJsonToPaginationResultFleet",
          "children": [
            {
              "name": "ConvertFrom-TorizonPlatformAPIJsonToPaginationResultFleet"
            }
          ]
        },
        {
          "name": "TorizonPlatformAPIPaginationResultNetworkInfo",
          "children": [
            {
              "name": "Initialize-TorizonPlatformAPIPaginationResultNetworkInfo"
            }
          ]
        },
        {
          "name": "TorizonPlatformAPIJsonToPaginationResultNetworkInfo",
          "children": [
            {
              "name": "ConvertFrom-TorizonPlatformAPIJsonToPaginationResultNetworkInfo"
            }
          ]
        },
        {
          "name": "TorizonPlatformAPIPaginationResultPackage",
          "children": [
            {
              "name": "Initialize-TorizonPlatformAPIPaginationResultPackage"
            }
          ]
        },
        {
          "name": "TorizonPlatformAPIJsonToPaginationResultPackage",
          "children": [
            {
              "name": "ConvertFrom-TorizonPlatformAPIJsonToPaginationResultPackage"
            }
          ]
        },
        {
          "name": "TorizonPlatformAPIPaginationResultString",
          "children": [
            {
              "name": "Initialize-TorizonPlatformAPIPaginationResultString"
            }
          ]
        },
        {
          "name": "TorizonPlatformAPIJsonToPaginationResultString",
          "children": [
            {
              "name": "ConvertFrom-TorizonPlatformAPIJsonToPaginationResultString"
            }
          ]
        },
        {
          "name": "TorizonPlatformAPIProvisionInfo",
          "children": [
            {
              "name": "Initialize-TorizonPlatformAPIProvisionInfo"
            }
          ]
        },
        {
          "name": "TorizonPlatformAPIJsonToProvisionInfo",
          "children": [
            {
              "name": "ConvertFrom-TorizonPlatformAPIJsonToProvisionInfo"
            }
          ]
        },
        {
          "name": "TorizonPlatformAPIQueueResponse",
          "children": [
            {
              "name": "Initialize-TorizonPlatformAPIQueueResponse"
            }
          ]
        },
        {
          "name": "TorizonPlatformAPIJsonToQueueResponse",
          "children": [
            {
              "name": "ConvertFrom-TorizonPlatformAPIJsonToQueueResponse"
            }
          ]
        },
        {
          "name": "TorizonPlatformAPIRangeNotSatisfiableRepr",
          "children": [
            {
              "name": "Initialize-TorizonPlatformAPIRangeNotSatisfiableRepr"
            }
          ]
        },
        {
          "name": "TorizonPlatformAPIJsonToRangeNotSatisfiableRepr",
          "children": [
            {
              "name": "ConvertFrom-TorizonPlatformAPIJsonToRangeNotSatisfiableRepr"
            }
          ]
        },
        {
          "name": "TorizonPlatformAPISeries",
          "children": [
            {
              "name": "Initialize-TorizonPlatformAPISeries"
            }
          ]
        },
        {
          "name": "TorizonPlatformAPIJsonToSeries",
          "children": [
            {
              "name": "ConvertFrom-TorizonPlatformAPIJsonToSeries"
            }
          ]
        },
        {
          "name": "TorizonPlatformAPISeriesMeta",
          "children": [
            {
              "name": "Initialize-TorizonPlatformAPISeriesMeta"
            }
          ]
        },
        {
          "name": "TorizonPlatformAPIJsonToSeriesMeta",
          "children": [
            {
              "name": "ConvertFrom-TorizonPlatformAPIJsonToSeriesMeta"
            }
          ]
        },
        {
          "name": "TorizonPlatformAPISimpleDeviceInfo",
          "children": [
            {
              "name": "Initialize-TorizonPlatformAPISimpleDeviceInfo"
            }
          ]
        },
        {
          "name": "TorizonPlatformAPIJsonToSimpleDeviceInfo",
          "children": [
            {
              "name": "ConvertFrom-TorizonPlatformAPIJsonToSimpleDeviceInfo"
            }
          ]
        },
        {
          "name": "TorizonPlatformAPISimpleDeviceNotAffectedInfo",
          "children": [
            {
              "name": "Initialize-TorizonPlatformAPISimpleDeviceNotAffectedInfo"
            }
          ]
        },
        {
          "name": "TorizonPlatformAPIJsonToSimpleDeviceNotAffectedInfo",
          "children": [
            {
              "name": "ConvertFrom-TorizonPlatformAPIJsonToSimpleDeviceNotAffectedInfo"
            }
          ]
        },
        {
          "name": "TorizonPlatformAPITargetImage",
          "children": [
            {
              "name": "Initialize-TorizonPlatformAPITargetImage"
            }
          ]
        },
        {
          "name": "TorizonPlatformAPIJsonToTargetImage",
          "children": [
            {
              "name": "ConvertFrom-TorizonPlatformAPIJsonToTargetImage"
            }
          ]
        },
        {
          "name": "TorizonPlatformAPITimeAggregation",
          "children": [
            {
              "name": "Initialize-TorizonPlatformAPITimeAggregation"
            }
          ]
        },
        {
          "name": "TorizonPlatformAPIJsonToTimeAggregation",
          "children": [
            {
              "name": "ConvertFrom-TorizonPlatformAPIJsonToTimeAggregation"
            }
          ]
        },
        {
          "name": "TorizonPlatformAPIJsonToTimeAggregationMethod",
          "children": [
            {
              "name": "ConvertFrom-TorizonPlatformAPIJsonToTimeAggregationMethod"
            }
          ]
        },
        {
          "name": "TorizonPlatformAPITuple2DeviceTagIdDeviceTagValue",
          "children": [
            {
              "name": "Initialize-TorizonPlatformAPITuple2DeviceTagIdDeviceTagValue"
            }
          ]
        },
        {
          "name": "TorizonPlatformAPIJsonToTuple2DeviceTagIdDeviceTagValue",
          "children": [
            {
              "name": "ConvertFrom-TorizonPlatformAPIJsonToTuple2DeviceTagIdDeviceTagValue"
            }
          ]
        },
        {
          "name": "TorizonPlatformAPITuple2LongOptionDouble",
          "children": [
            {
              "name": "Initialize-TorizonPlatformAPITuple2LongOptionDouble"
            }
          ]
        },
        {
          "name": "TorizonPlatformAPIJsonToTuple2LongOptionDouble",
          "children": [
            {
              "name": "ConvertFrom-TorizonPlatformAPIJsonToTuple2LongOptionDouble"
            }
          ]
        },
        {
          "name": "TorizonPlatformAPIUpdateCreateResult",
          "children": [
            {
              "name": "Initialize-TorizonPlatformAPIUpdateCreateResult"
            }
          ]
        },
        {
          "name": "TorizonPlatformAPIJsonToUpdateCreateResult",
          "children": [
            {
              "name": "ConvertFrom-TorizonPlatformAPIJsonToUpdateCreateResult"
            }
          ]
        },
        {
          "name": "TorizonPlatformAPIUpdateRequest",
          "children": [
            {
              "name": "Initialize-TorizonPlatformAPIUpdateRequest"
            }
          ]
        },
        {
          "name": "TorizonPlatformAPIJsonToUpdateRequest",
          "children": [
            {
              "name": "ConvertFrom-TorizonPlatformAPIJsonToUpdateRequest"
            }
          ]
        },
        {
          "name": "TorizonPlatformAPIUpstreamEndpointErrorRepr",
          "children": [
            {
              "name": "Initialize-TorizonPlatformAPIUpstreamEndpointErrorRepr"
            }
          ]
        },
        {
          "name": "TorizonPlatformAPIJsonToUpstreamEndpointErrorRepr",
          "children": [
            {
              "name": "ConvertFrom-TorizonPlatformAPIJsonToUpstreamEndpointErrorRepr"
            }
          ]
        },
        {
          "name": "TorizonPlatformAPIConfiguration",
          "children": [
            {
              "name": "Get-TorizonPlatformAPIConfiguration"
            },
            {
              "name": "Set-TorizonPlatformAPIConfiguration"
            }
          ]
        },
        {
          "name": "TorizonPlatformAPIConfigurationApiKey",
          "children": [
            {
              "name": "Set-TorizonPlatformAPIConfigurationApiKey"
            }
          ]
        },
        {
          "name": "TorizonPlatformAPIConfigurationApiKeyPrefix",
          "children": [
            {
              "name": "Set-TorizonPlatformAPIConfigurationApiKeyPrefix"
            }
          ]
        },
        {
          "name": "TorizonPlatformAPIConfigurationDefaultHeader",
          "children": [
            {
              "name": "Set-TorizonPlatformAPIConfigurationDefaultHeader"
            }
          ]
        },
        {
          "name": "TorizonPlatformAPIHostSetting",
          "children": [
            {
              "name": "Get-TorizonPlatformAPIHostSetting"
            }
          ]
        },
        {
          "name": "TorizonPlatformAPIUrlFromHostSetting",
          "children": [
            {
              "name": "Get-TorizonPlatformAPIUrlFromHostSetting"
            }
          ]
        },
        {
          "name": "TorizonPlatformAPIConfigurationHttpSigning",
          "children": [
            {
              "name": "Set-TorizonPlatformAPIConfigurationHttpSigning"
            },
            {
              "name": "Get-TorizonPlatformAPIConfigurationHttpSigning"
            }
          ]
        }
      ]
    }
  ]
}
