{
  "name": "Cargonautica",
  "children": [
    {
      "name": "binGist",
      "companyName": "Cargonautica",
      "children": [
        {
          "name": "BinaryGist",
          "children": [
            {
              "name": "New-BinaryGist"
            }
          ]
        }
      ]
    },
    {
      "name": "PSBolts",
      "companyName": "Cargonautica",
      "children": [
        {
          "name": "ModuleNounsAndVerbs",
          "children": [
            {
              "name": "Get-ModuleNounsAndVerbs"
            }
          ]
        },
        {
          "name": "MultipartFormDataUpload",
          "children": [
            {
              "name": "Invoke-MultipartFormDataUpload"
            }
          ]
        },
        {
          "name": "TimestampMessage",
          "children": [
            {
              "name": "New-TimestampMessage"
            }
          ]
        }
      ]
    },
    {
      "name": "WindowsOfflineUpdate",
      "companyName": "Cargonautica",
      "children": [
        {
          "name": "WimFileFromISO",
          "children": [
            {
              "name": "Extract-WimFileFromISO"
            }
          ]
        },
        {
          "name": "LatestUpdate",
          "children": [
            {
              "name": "Find-LatestUpdate"
            }
          ]
        }
      ]
    },
    {
      "name": "WindowsOEMinformation",
      "companyName": "Cargonautica",
      "children": [
        {
          "name": "WindowsOemInformation",
          "children": [
            {
              "name": "Set-WindowsOemInformation"
            }
          ]
        }
      ]
    }
  ]
}
